adaptive_trainer/__init__.py
adaptive_trainer/collators.py
adaptive_trainer/config.py
adaptive_trainer/data_processors.py
adaptive_trainer/trainers.py
adaptive_trainer/training.py
adaptive_trainer/utils.py
adaptive_trainer-0.0.6.dist-info/METADATA
adaptive_trainer-0.0.6.dist-info/WHEEL
adaptive_trainer-0.0.6.dist-info/licenses/LICENSE
adaptive_trainer-0.0.6.dist-info/RECORD
