Metadata-Version: 2.4
Name: adaptive_trainer
Version: 0.0.6
Summary: A Hugging Face Trainer extension for adaptive loss and ideas learning.
Project-URL: Homepage, https://github.com/samarthpusalkar/Adaptive_Trainer
Project-URL: Issues, https://github.com/samarthpusalkar/Adaptive_Trainer/issues
Author-email: Samarth Pusalkar <samarthpusalkar@gmail.com>
License-Expression: Apache-2.0
License-File: LICENSE
Keywords: adaptive loss,deep learning,huggingface,ideas learning,machine learning,nlp,trainer,transformers
Classifier: Development Status :: 1 - Planning
Classifier: Intended Audience :: Developers
Classifier: Intended Audience :: Science/Research
Classifier: Operating System :: OS Independent
Classifier: Programming Language :: Python :: 3
Classifier: Topic :: Scientific/Engineering :: Artificial Intelligence
Classifier: Topic :: Software Development
Classifier: Topic :: Software Development :: Libraries :: Python Modules
Requires-Python: >=3.9
Requires-Dist: accelerate>=1.6.0
Requires-Dist: datasets>=3.6.0
Requires-Dist: huggingface-hub>=0.31.1
Requires-Dist: torch>=2.6.0
Requires-Dist: transformers>=4.52.3
Requires-Dist: wandb>=0.19.11
Provides-Extra: flash-attn
Requires-Dist: bitsandbytes>=0.45.5; extra == 'flash-attn'
Requires-Dist: flash-attn>=2.7.4; extra == 'flash-attn'
